hibp_downloader-0.3.4.dist-info/METADATA
hibp_downloader-0.3.4.dist-info/WHEEL
hibp_downloader-0.3.4.dist-info/entry_points.txt
hibp_downloader-0.3.4.dist-info/licenses/LICENSE
hibp_downloader/__init__.py
hibp_downloader/commands/hibp_download.py
hibp_downloader/commands/hibp_generate.py
hibp_downloader/commands/hibp_query.py
hibp_downloader/exceptions.py
hibp_downloader/lib/app.py
hibp_downloader/lib/filedata.py
hibp_downloader/lib/generators.py
hibp_downloader/lib/hashing.py
hibp_downloader/lib/http.py
hibp_downloader/lib/logger.py
hibp_downloader/lib/md4.py
hibp_downloader/main.py
hibp_downloader/models/__init__.py
hibp_downloader/models/app_context.py
hibp_downloader/models/hash_type.py
hibp_downloader/models/prefix_metadata.py
hibp_downloader/models/stats.py
hibp_downloader/models/worker_args.py
hibp_downloader/py.typed
hibp_downloader-0.3.4.dist-info/RECORD
