Metadata-Version: 2.1
Name: hibp-downloader
Version: 0.3.4
Summary: Efficiently download HIBP new pwned password data by hash-prefix for a local-copy
Keywords: hibp-downloader,hibp,haveibeenpwned,haveibeenpwned-downloader,sha1,ntlm
Author-Email: Nicholas de Jong <ndejong@threatpatrols.com>
License: BSD-3-Clause
Classifier: Environment :: Console
Classifier: Intended Audience :: System Administrators
Classifier: License :: OSI Approved :: BSD License
Classifier: Programming Language :: Python :: 3.8
Classifier: Programming Language :: Python :: 3.9
Classifier: Programming Language :: Python :: 3.10
Classifier: Programming Language :: Python :: 3.11
Classifier: Programming Language :: Python :: 3.12
Project-URL: Documentation, https://threatpatrols.github.io/hibp-downloader
Project-URL: Homepage, https://github.com/threatpatrols/hibp-downloader
Project-URL: Repository, https://github.com/threatpatrols/hibp-downloader
Project-URL: Bug Tracker, https://github.com/threatpatrols/hibp-downloader/issues
Requires-Python: <4,>=3.8
Requires-Dist: httpx[http2]>=0.21
Requires-Dist: httpcore>=0.14
Requires-Dist: aiofiles>=0.8
Requires-Dist: typer>=0.9.0
Requires-Dist: shellingham>=1.3.0
